{
  "the-mom-test": {
    "title": "The Mom Test",
    "author": "Rob Fitzpatrick",
    "style": "sticker",
    "providerPrompt": "Create a text-free vertical icon illustration for a premium mobile learning app book tile. Concept seed: How to talk to customers and learn the truth when everyone is lying to you — including your mom. Reader situation: You are about to build something and want to find out whether anyone actually needs it, before you spend a year finding out the hard way. Required symbol: one microphone pointed at a small evidence dot. Required palette: solid bright turquoise background (#0096a6), accent #ffd51f, highlight #ff6b3d. Style variation: large sticker emblem. Make the symbol feel like one bold app sticker on a flat color field, with a thick clean outline and slight offset shadow. Use a playful, high-contrast Duolingo or Headway-like app illustration energy, but keep it premium. The emblem should occupy 45-55% of the upper canvas. Avoid tiny details. The result should be instantly recognizable from across the room. The background must remain one unbroken solid primary color across the entire image, including the bottom 44% where the title plate will sit. Do not add a darker footer, lower band, vignette, or separate bottom block. Make the books visibly different from each other by using the required primary background color strongly. The final set should not look like variations of the same navy/teal cover. Memorability standard: the image must read instantly at a tiny thumbnail size. If the idea needs more than one emblem, simplify it. Style: flat 2D illustration, bold geometric shapes, crisp edges, premium editorial taste, not photorealistic, not painterly, not collage. Composition standard: one centered emblem in the upper 56% of the 2:3 vertical canvas, generous negative space, no scene, no background environment, no depth-of-field, no realistic room, no hands. Simplicity limit: use one main object and at most one supporting shape. Avoid clusters, crowds, many lines, tiny parts, diagrams, dashboards, maps with detail, charts, documents, UI, and decorative clutter. Background standard: perfectly solid matte color field or a nearly solid field with only extremely subtle paper grain. No gradients behind the future title plate, no pattern fields, no texture-heavy backgrounds. Color standard: very high contrast and memorable. Use the required palette strongly so this book looks different from the others. Avoid beige, gray, washed-out neutrals, muddy gradients, monochrome palettes, and low-contrast pastel art. Hard no-text rule: no letters, no words, no book title, no author name, no numbers, no punctuation marks, no fake glyphs, no interface icons, no logos, no labels, no signage. Avoid literal speech bubbles, question marks, documents with writing, screens with UI, pages with text, book mockups, or any surface that could look like typography. Keep the bottom 44% visually calm and the same solid primary background color because the website will place matching title text over that area. Do not create a physical book cover, 3D book object, product photo, border, page spine, drop shadow, room background, hands, or a book sitting on a surface."
  },
  "thinking-fast-and-slow": {
    "title": "Thinking, Fast and Slow",
    "author": "Daniel Kahneman",
    "style": "sticker",
    "providerPrompt": "Create a text-free vertical icon illustration for a premium mobile learning app book tile. Concept seed: A map of the two systems that run your mind — and the predictable ways the fast one fools you. Reader situation: You make judgments under uncertainty for a living — hiring, investing, forecasting, designing — and want to know where your intuition is trustworthy and where it is confidently wrong. Required symbol: two simple paths, one lightning bolt and one slow curve. Required palette: solid magenta burgundy background (#9c114c), accent #ffd51f, highlight #25d6ff. Style variation: large sticker emblem. Make the symbol feel like one bold app sticker on a flat color field, with a thick clean outline and slight offset shadow. Use a playful, high-contrast Duolingo or Headway-like app illustration energy, but keep it premium. The emblem should occupy 45-55% of the upper canvas. Avoid tiny details. The result should be instantly recognizable from across the room. The background must remain one unbroken solid primary color across the entire image, including the bottom 44% where the title plate will sit. Do not add a darker footer, lower band, vignette, or separate bottom block. Make the books visibly different from each other by using the required primary background color strongly. The final set should not look like variations of the same navy/teal cover. Memorability standard: the image must read instantly at a tiny thumbnail size. If the idea needs more than one emblem, simplify it. Style: flat 2D illustration, bold geometric shapes, crisp edges, premium editorial taste, not photorealistic, not painterly, not collage. Composition standard: one centered emblem in the upper 56% of the 2:3 vertical canvas, generous negative space, no scene, no background environment, no depth-of-field, no realistic room, no hands. Simplicity limit: use one main object and at most one supporting shape. Avoid clusters, crowds, many lines, tiny parts, diagrams, dashboards, maps with detail, charts, documents, UI, and decorative clutter. Background standard: perfectly solid matte color field or a nearly solid field with only extremely subtle paper grain. No gradients behind the future title plate, no pattern fields, no texture-heavy backgrounds. Color standard: very high contrast and memorable. Use the required palette strongly so this book looks different from the others. Avoid beige, gray, washed-out neutrals, muddy gradients, monochrome palettes, and low-contrast pastel art. Hard no-text rule: no letters, no words, no book title, no author name, no numbers, no punctuation marks, no fake glyphs, no interface icons, no logos, no labels, no signage. Avoid literal speech bubbles, question marks, documents with writing, screens with UI, pages with text, book mockups, or any surface that could look like typography. Keep the bottom 44% visually calm and the same solid primary background color because the website will place matching title text over that area. Do not create a physical book cover, 3D book object, product photo, border, page spine, drop shadow, room background, hands, or a book sitting on a surface."
  },
  "the-wisdom-of-crowds": {
    "title": "The Wisdom of Crowds",
    "author": "James Surowiecki",
    "style": "sticker",
    "providerPrompt": "Create a text-free vertical icon illustration for a premium mobile learning app book tile. Concept seed: Why large groups of ordinary people outguess experts — and the exact conditions under which they stop. Reader situation: You aggregate opinions for a living — running teams, markets, forecasts, or feedback systems — and want to know when the average answer is smart and when it is a stampede. Required symbol: one large signal formed by many tiny dots. Required palette: solid royal blue background (#0877d9), accent #37f5ff, highlight #ffbd2e. Style variation: large sticker emblem. Make the symbol feel like one bold app sticker on a flat color field, with a thick clean outline and slight offset shadow. Use a playful, high-contrast Duolingo or Headway-like app illustration energy, but keep it premium. The emblem should occupy 45-55% of the upper canvas. Avoid tiny details. The result should be instantly recognizable from across the room. The background must remain one unbroken solid primary color across the entire image, including the bottom 44% where the title plate will sit. Do not add a darker footer, lower band, vignette, or separate bottom block. Make the books visibly different from each other by using the required primary background color strongly. The final set should not look like variations of the same navy/teal cover. Memorability standard: the image must read instantly at a tiny thumbnail size. If the idea needs more than one emblem, simplify it. Style: flat 2D illustration, bold geometric shapes, crisp edges, premium editorial taste, not photorealistic, not painterly, not collage. Composition standard: one centered emblem in the upper 56% of the 2:3 vertical canvas, generous negative space, no scene, no background environment, no depth-of-field, no realistic room, no hands. Simplicity limit: use one main object and at most one supporting shape. Avoid clusters, crowds, many lines, tiny parts, diagrams, dashboards, maps with detail, charts, documents, UI, and decorative clutter. Background standard: perfectly solid matte color field or a nearly solid field with only extremely subtle paper grain. No gradients behind the future title plate, no pattern fields, no texture-heavy backgrounds. Color standard: very high contrast and memorable. Use the required palette strongly so this book looks different from the others. Avoid beige, gray, washed-out neutrals, muddy gradients, monochrome palettes, and low-contrast pastel art. Hard no-text rule: no letters, no words, no book title, no author name, no numbers, no punctuation marks, no fake glyphs, no interface icons, no logos, no labels, no signage. Avoid literal speech bubbles, question marks, documents with writing, screens with UI, pages with text, book mockups, or any surface that could look like typography. Keep the bottom 44% visually calm and the same solid primary background color because the website will place matching title text over that area. Do not create a physical book cover, 3D book object, product photo, border, page spine, drop shadow, room background, hands, or a book sitting on a surface."
  },
  "seeing-like-a-state": {
    "title": "Seeing Like a State",
    "author": "James C. Scott",
    "style": "sticker",
    "providerPrompt": "Create a text-free vertical icon illustration for a premium mobile learning app book tile. Concept seed: Why grand schemes to improve the human condition fail: they replace messy local knowledge with tidy maps, then mistake the map for the territory. Reader situation: You design systems for other people — software, processes, org charts, cities — and want to understand why clean top-down plans keep being defeated by messy reality. Required symbol: one map grid interrupted by a living tree root. Required palette: solid electric blue background (#006bff), accent #fff4da, highlight #ff6b1a. Style variation: large sticker emblem. Make the symbol feel like one bold app sticker on a flat color field, with a thick clean outline and slight offset shadow. Use a playful, high-contrast Duolingo or Headway-like app illustration energy, but keep it premium. The emblem should occupy 45-55% of the upper canvas. Avoid tiny details. The result should be instantly recognizable from across the room. The background must remain one unbroken solid primary color across the entire image, including the bottom 44% where the title plate will sit. Do not add a darker footer, lower band, vignette, or separate bottom block. Make the books visibly different from each other by using the required primary background color strongly. The final set should not look like variations of the same navy/teal cover. Memorability standard: the image must read instantly at a tiny thumbnail size. If the idea needs more than one emblem, simplify it. Style: flat 2D illustration, bold geometric shapes, crisp edges, premium editorial taste, not photorealistic, not painterly, not collage. Composition standard: one centered emblem in the upper 56% of the 2:3 vertical canvas, generous negative space, no scene, no background environment, no depth-of-field, no realistic room, no hands. Simplicity limit: use one main object and at most one supporting shape. Avoid clusters, crowds, many lines, tiny parts, diagrams, dashboards, maps with detail, charts, documents, UI, and decorative clutter. Background standard: perfectly solid matte color field or a nearly solid field with only extremely subtle paper grain. No gradients behind the future title plate, no pattern fields, no texture-heavy backgrounds. Color standard: very high contrast and memorable. Use the required palette strongly so this book looks different from the others. Avoid beige, gray, washed-out neutrals, muddy gradients, monochrome palettes, and low-contrast pastel art. Hard no-text rule: no letters, no words, no book title, no author name, no numbers, no punctuation marks, no fake glyphs, no interface icons, no logos, no labels, no signage. Avoid literal speech bubbles, question marks, documents with writing, screens with UI, pages with text, book mockups, or any surface that could look like typography. Keep the bottom 44% visually calm and the same solid primary background color because the website will place matching title text over that area. Do not create a physical book cover, 3D book object, product photo, border, page spine, drop shadow, room background, hands, or a book sitting on a surface."
  },
  "the-structure-of-scientific-revolutions": {
    "title": "The Structure of Scientific Revolutions",
    "author": "Thomas S. Kuhn",
    "style": "sticker",
    "providerPrompt": "Create a text-free vertical icon illustration for a premium mobile learning app book tile. Concept seed: Science doesn't progress by smooth accumulation — it alternates between puzzle-solving within a paradigm and rare, wrenching revolutions that replace it. Reader situation: You're deciding whether to keep refining the current approach or throw it out — in research, strategy, or engineering — and want a vocabulary for telling incremental progress from a dying framework. Required symbol: one orbit ring breaking and reforming around a cube. Required palette: solid deep indigo background (#3432c7), accent #7dffcf, highlight #ff8a1f. Style variation: large sticker emblem. Make the symbol feel like one bold app sticker on a flat color field, with a thick clean outline and slight offset shadow. Use a playful, high-contrast Duolingo or Headway-like app illustration energy, but keep it premium. The emblem should occupy 45-55% of the upper canvas. Avoid tiny details. The result should be instantly recognizable from across the room. The background must remain one unbroken solid primary color across the entire image, including the bottom 44% where the title plate will sit. Do not add a darker footer, lower band, vignette, or separate bottom block. Make the books visibly different from each other by using the required primary background color strongly. The final set should not look like variations of the same navy/teal cover. Memorability standard: the image must read instantly at a tiny thumbnail size. If the idea needs more than one emblem, simplify it. Style: flat 2D illustration, bold geometric shapes, crisp edges, premium editorial taste, not photorealistic, not painterly, not collage. Composition standard: one centered emblem in the upper 56% of the 2:3 vertical canvas, generous negative space, no scene, no background environment, no depth-of-field, no realistic room, no hands. Simplicity limit: use one main object and at most one supporting shape. Avoid clusters, crowds, many lines, tiny parts, diagrams, dashboards, maps with detail, charts, documents, UI, and decorative clutter. Background standard: perfectly solid matte color field or a nearly solid field with only extremely subtle paper grain. No gradients behind the future title plate, no pattern fields, no texture-heavy backgrounds. Color standard: very high contrast and memorable. Use the required palette strongly so this book looks different from the others. Avoid beige, gray, washed-out neutrals, muddy gradients, monochrome palettes, and low-contrast pastel art. Hard no-text rule: no letters, no words, no book title, no author name, no numbers, no punctuation marks, no fake glyphs, no interface icons, no logos, no labels, no signage. Avoid literal speech bubbles, question marks, documents with writing, screens with UI, pages with text, book mockups, or any surface that could look like typography. Keep the bottom 44% visually calm and the same solid primary background color because the website will place matching title text over that area. Do not create a physical book cover, 3D book object, product photo, border, page spine, drop shadow, room background, hands, or a book sitting on a surface."
  },
  "good-strategy-bad-strategy": {
    "title": "Good Strategy Bad Strategy",
    "author": "Richard Rumelt",
    "style": "sticker",
    "providerPrompt": "Create a text-free vertical icon illustration for a premium mobile learning app book tile. Concept seed: Why strategy is not ambition, values, or a list of goals - it is a diagnosis, a guiding policy, and coherent action. Reader situation: You keep calling goals strategy, or your team has priorities but no real explanation of where to concentrate force. Required symbol: one chess knight aimed at a target dot. Required palette: solid vermilion red background (#f23a1f), accent #15d0c8, highlight #fff1cc. Style variation: large sticker emblem. Make the symbol feel like one bold app sticker on a flat color field, with a thick clean outline and slight offset shadow. Use a playful, high-contrast Duolingo or Headway-like app illustration energy, but keep it premium. The emblem should occupy 45-55% of the upper canvas. Avoid tiny details. The result should be instantly recognizable from across the room. The background must remain one unbroken solid primary color across the entire image, including the bottom 44% where the title plate will sit. Do not add a darker footer, lower band, vignette, or separate bottom block. Make the books visibly different from each other by using the required primary background color strongly. The final set should not look like variations of the same navy/teal cover. Memorability standard: the image must read instantly at a tiny thumbnail size. If the idea needs more than one emblem, simplify it. Style: flat 2D illustration, bold geometric shapes, crisp edges, premium editorial taste, not photorealistic, not painterly, not collage. Composition standard: one centered emblem in the upper 56% of the 2:3 vertical canvas, generous negative space, no scene, no background environment, no depth-of-field, no realistic room, no hands. Simplicity limit: use one main object and at most one supporting shape. Avoid clusters, crowds, many lines, tiny parts, diagrams, dashboards, maps with detail, charts, documents, UI, and decorative clutter. Background standard: perfectly solid matte color field or a nearly solid field with only extremely subtle paper grain. No gradients behind the future title plate, no pattern fields, no texture-heavy backgrounds. Color standard: very high contrast and memorable. Use the required palette strongly so this book looks different from the others. Avoid beige, gray, washed-out neutrals, muddy gradients, monochrome palettes, and low-contrast pastel art. Hard no-text rule: no letters, no words, no book title, no author name, no numbers, no punctuation marks, no fake glyphs, no interface icons, no logos, no labels, no signage. Avoid literal speech bubbles, question marks, documents with writing, screens with UI, pages with text, book mockups, or any surface that could look like typography. Keep the bottom 44% visually calm and the same solid primary background color because the website will place matching title text over that area. Do not create a physical book cover, 3D book object, product photo, border, page spine, drop shadow, room background, hands, or a book sitting on a surface."
  },
  "the-lean-startup": {
    "title": "The Lean Startup",
    "author": "Eric Ries",
    "style": "sticker",
    "providerPrompt": "Create a text-free vertical icon illustration for a premium mobile learning app book tile. Concept seed: A method for learning under extreme uncertainty: build the smallest thing that tests the riskiest assumption, measure honestly, and learn before you run out of time. Reader situation: You are tempted to build a complete product before you know whether the underlying customer, value, or growth assumptions are true. Required symbol: one small rocket made from a triangle and circle. Required palette: solid vivid violet background (#7c2cff), accent #aaff24, highlight #ff8a1f. Style variation: large sticker emblem. Make the symbol feel like one bold app sticker on a flat color field, with a thick clean outline and slight offset shadow. Use a playful, high-contrast Duolingo or Headway-like app illustration energy, but keep it premium. The emblem should occupy 45-55% of the upper canvas. Avoid tiny details. The result should be instantly recognizable from across the room. The background must remain one unbroken solid primary color across the entire image, including the bottom 44% where the title plate will sit. Do not add a darker footer, lower band, vignette, or separate bottom block. Make the books visibly different from each other by using the required primary background color strongly. The final set should not look like variations of the same navy/teal cover. Memorability standard: the image must read instantly at a tiny thumbnail size. If the idea needs more than one emblem, simplify it. Style: flat 2D illustration, bold geometric shapes, crisp edges, premium editorial taste, not photorealistic, not painterly, not collage. Composition standard: one centered emblem in the upper 56% of the 2:3 vertical canvas, generous negative space, no scene, no background environment, no depth-of-field, no realistic room, no hands. Simplicity limit: use one main object and at most one supporting shape. Avoid clusters, crowds, many lines, tiny parts, diagrams, dashboards, maps with detail, charts, documents, UI, and decorative clutter. Background standard: perfectly solid matte color field or a nearly solid field with only extremely subtle paper grain. No gradients behind the future title plate, no pattern fields, no texture-heavy backgrounds. Color standard: very high contrast and memorable. Use the required palette strongly so this book looks different from the others. Avoid beige, gray, washed-out neutrals, muddy gradients, monochrome palettes, and low-contrast pastel art. Hard no-text rule: no letters, no words, no book title, no author name, no numbers, no punctuation marks, no fake glyphs, no interface icons, no logos, no labels, no signage. Avoid literal speech bubbles, question marks, documents with writing, screens with UI, pages with text, book mockups, or any surface that could look like typography. Keep the bottom 44% visually calm and the same solid primary background color because the website will place matching title text over that area. Do not create a physical book cover, 3D book object, product photo, border, page spine, drop shadow, room background, hands, or a book sitting on a surface."
  },
  "dont-make-me-think": {
    "title": "Don't Make Me Think",
    "author": "Steve Krug",
    "style": "sticker",
    "providerPrompt": "Create a text-free vertical icon illustration for a premium mobile learning app book tile. Concept seed: A usability classic built on one standard: a page works when users can understand what it is, what they can do, and where to go without decoding it. Reader situation: Your product page, catalog, guide, or app screen is visually polished but users still hesitate, bounce, or ask what they are supposed to do. Required symbol: one oversized cursor pointing at a clear doorway. Required palette: solid saturated purple background (#6a24d8), accent #b7ff1f, highlight #ffffff. Style variation: large sticker emblem. Make the symbol feel like one bold app sticker on a flat color field, with a thick clean outline and slight offset shadow. Use a playful, high-contrast Duolingo or Headway-like app illustration energy, but keep it premium. The emblem should occupy 45-55% of the upper canvas. Avoid tiny details. The result should be instantly recognizable from across the room. The background must remain one unbroken solid primary color across the entire image, including the bottom 44% where the title plate will sit. Do not add a darker footer, lower band, vignette, or separate bottom block. Make the books visibly different from each other by using the required primary background color strongly. The final set should not look like variations of the same navy/teal cover. Memorability standard: the image must read instantly at a tiny thumbnail size. If the idea needs more than one emblem, simplify it. Style: flat 2D illustration, bold geometric shapes, crisp edges, premium editorial taste, not photorealistic, not painterly, not collage. Composition standard: one centered emblem in the upper 56% of the 2:3 vertical canvas, generous negative space, no scene, no background environment, no depth-of-field, no realistic room, no hands. Simplicity limit: use one main object and at most one supporting shape. Avoid clusters, crowds, many lines, tiny parts, diagrams, dashboards, maps with detail, charts, documents, UI, and decorative clutter. Background standard: perfectly solid matte color field or a nearly solid field with only extremely subtle paper grain. No gradients behind the future title plate, no pattern fields, no texture-heavy backgrounds. Color standard: very high contrast and memorable. Use the required palette strongly so this book looks different from the others. Avoid beige, gray, washed-out neutrals, muddy gradients, monochrome palettes, and low-contrast pastel art. Hard no-text rule: no letters, no words, no book title, no author name, no numbers, no punctuation marks, no fake glyphs, no interface icons, no logos, no labels, no signage. Avoid literal speech bubbles, question marks, documents with writing, screens with UI, pages with text, book mockups, or any surface that could look like typography. Keep the bottom 44% visually calm and the same solid primary background color because the website will place matching title text over that area. Do not create a physical book cover, 3D book object, product photo, border, page spine, drop shadow, room background, hands, or a book sitting on a surface."
  },
  "made-to-stick": {
    "title": "Made to Stick",
    "author": "Chip Heath and Dan Heath",
    "style": "sticker",
    "providerPrompt": "Create a text-free vertical icon illustration for a premium mobile learning app book tile. Concept seed: Why some ideas survive and spread: they are simple, unexpected, concrete, credible, emotional, and carried by stories. Reader situation: You understand your idea but cannot make other people remember, repeat, or act on it. Required symbol: one bright pin holding a simple idea card. Required palette: solid sunflower yellow background (#ffc21a), accent #1647d9, highlight #111111. Style variation: large sticker emblem. Make the symbol feel like one bold app sticker on a flat color field, with a thick clean outline and slight offset shadow. Use a playful, high-contrast Duolingo or Headway-like app illustration energy, but keep it premium. The emblem should occupy 45-55% of the upper canvas. Avoid tiny details. The result should be instantly recognizable from across the room. The background must remain one unbroken solid primary color across the entire image, including the bottom 44% where the title plate will sit. Do not add a darker footer, lower band, vignette, or separate bottom block. Make the books visibly different from each other by using the required primary background color strongly. The final set should not look like variations of the same navy/teal cover. Memorability standard: the image must read instantly at a tiny thumbnail size. If the idea needs more than one emblem, simplify it. Style: flat 2D illustration, bold geometric shapes, crisp edges, premium editorial taste, not photorealistic, not painterly, not collage. Composition standard: one centered emblem in the upper 56% of the 2:3 vertical canvas, generous negative space, no scene, no background environment, no depth-of-field, no realistic room, no hands. Simplicity limit: use one main object and at most one supporting shape. Avoid clusters, crowds, many lines, tiny parts, diagrams, dashboards, maps with detail, charts, documents, UI, and decorative clutter. Background standard: perfectly solid matte color field or a nearly solid field with only extremely subtle paper grain. No gradients behind the future title plate, no pattern fields, no texture-heavy backgrounds. Color standard: very high contrast and memorable. Use the required palette strongly so this book looks different from the others. Avoid beige, gray, washed-out neutrals, muddy gradients, monochrome palettes, and low-contrast pastel art. Hard no-text rule: no letters, no words, no book title, no author name, no numbers, no punctuation marks, no fake glyphs, no interface icons, no logos, no labels, no signage. Avoid literal speech bubbles, question marks, documents with writing, screens with UI, pages with text, book mockups, or any surface that could look like typography. Keep the bottom 44% visually calm and the same solid primary background color because the website will place matching title text over that area. Do not create a physical book cover, 3D book object, product photo, border, page spine, drop shadow, room background, hands, or a book sitting on a surface."
  },
  "deep-work": {
    "title": "Deep Work",
    "author": "Cal Newport",
    "style": "sticker",
    "providerPrompt": "Create a text-free vertical icon illustration for a premium mobile learning app book tile. Concept seed: A practical argument that valuable work increasingly depends on protecting long, undistracted stretches of attention. Reader situation: Your day is full of Slack, email, meetings, and context switching, and the work that actually moves your life or company forward keeps getting postponed. Required symbol: one glowing desk lamp cone cutting through dark space. Required palette: solid electric cobalt blue background (#082f8f), accent #00d9ff, highlight #ffd447. Style variation: large sticker emblem. Make the symbol feel like one bold app sticker on a flat color field, with a thick clean outline and slight offset shadow. Use a playful, high-contrast Duolingo or Headway-like app illustration energy, but keep it premium. The emblem should occupy 45-55% of the upper canvas. Avoid tiny details. The result should be instantly recognizable from across the room. The background must remain one unbroken solid primary color across the entire image, including the bottom 44% where the title plate will sit. Do not add a darker footer, lower band, vignette, or separate bottom block. Make the books visibly different from each other by using the required primary background color strongly. The final set should not look like variations of the same navy/teal cover. Memorability standard: the image must read instantly at a tiny thumbnail size. If the idea needs more than one emblem, simplify it. Style: flat 2D illustration, bold geometric shapes, crisp edges, premium editorial taste, not photorealistic, not painterly, not collage. Composition standard: one centered emblem in the upper 56% of the 2:3 vertical canvas, generous negative space, no scene, no background environment, no depth-of-field, no realistic room, no hands. Simplicity limit: use one main object and at most one supporting shape. Avoid clusters, crowds, many lines, tiny parts, diagrams, dashboards, maps with detail, charts, documents, UI, and decorative clutter. Background standard: perfectly solid matte color field or a nearly solid field with only extremely subtle paper grain. No gradients behind the future title plate, no pattern fields, no texture-heavy backgrounds. Color standard: very high contrast and memorable. Use the required palette strongly so this book looks different from the others. Avoid beige, gray, washed-out neutrals, muddy gradients, monochrome palettes, and low-contrast pastel art. Hard no-text rule: no letters, no words, no book title, no author name, no numbers, no punctuation marks, no fake glyphs, no interface icons, no logos, no labels, no signage. Avoid literal speech bubbles, question marks, documents with writing, screens with UI, pages with text, book mockups, or any surface that could look like typography. Keep the bottom 44% visually calm and the same solid primary background color because the website will place matching title text over that area. Do not create a physical book cover, 3D book object, product photo, border, page spine, drop shadow, room background, hands, or a book sitting on a surface."
  },
  "getting-things-done": {
    "title": "Getting Things Done",
    "author": "David Allen",
    "style": "sticker",
    "providerPrompt": "Create a text-free vertical icon illustration for a premium mobile learning app book tile. Concept seed: A system for turning mental clutter into captured commitments, clear next actions, and regular review. Reader situation: Your head is full of open loops, reminders, half-decisions, and vague tasks that keep resurfacing at the worst possible time. Required symbol: three stacked blocks snapping into a single check shape. Required palette: solid bright teal background (#008c8c), accent #ff8a1f, highlight #ffffff. Style variation: large sticker emblem. Make the symbol feel like one bold app sticker on a flat color field, with a thick clean outline and slight offset shadow. Use a playful, high-contrast Duolingo or Headway-like app illustration energy, but keep it premium. The emblem should occupy 45-55% of the upper canvas. Avoid tiny details. The result should be instantly recognizable from across the room. The background must remain one unbroken solid primary color across the entire image, including the bottom 44% where the title plate will sit. Do not add a darker footer, lower band, vignette, or separate bottom block. Make the books visibly different from each other by using the required primary background color strongly. The final set should not look like variations of the same navy/teal cover. Memorability standard: the image must read instantly at a tiny thumbnail size. If the idea needs more than one emblem, simplify it. Style: flat 2D illustration, bold geometric shapes, crisp edges, premium editorial taste, not photorealistic, not painterly, not collage. Composition standard: one centered emblem in the upper 56% of the 2:3 vertical canvas, generous negative space, no scene, no background environment, no depth-of-field, no realistic room, no hands. Simplicity limit: use one main object and at most one supporting shape. Avoid clusters, crowds, many lines, tiny parts, diagrams, dashboards, maps with detail, charts, documents, UI, and decorative clutter. Background standard: perfectly solid matte color field or a nearly solid field with only extremely subtle paper grain. No gradients behind the future title plate, no pattern fields, no texture-heavy backgrounds. Color standard: very high contrast and memorable. Use the required palette strongly so this book looks different from the others. Avoid beige, gray, washed-out neutrals, muddy gradients, monochrome palettes, and low-contrast pastel art. Hard no-text rule: no letters, no words, no book title, no author name, no numbers, no punctuation marks, no fake glyphs, no interface icons, no logos, no labels, no signage. Avoid literal speech bubbles, question marks, documents with writing, screens with UI, pages with text, book mockups, or any surface that could look like typography. Keep the bottom 44% visually calm and the same solid primary background color because the website will place matching title text over that area. Do not create a physical book cover, 3D book object, product photo, border, page spine, drop shadow, room background, hands, or a book sitting on a surface."
  },
  "atomic-habits": {
    "title": "Atomic Habits",
    "author": "James Clear",
    "style": "sticker",
    "providerPrompt": "Create a text-free vertical icon illustration for a premium mobile learning app book tile. Concept seed: A behavior-change playbook built around small repeatable actions, identity, cues, and environment design. Reader situation: You keep trying to change by motivation alone and then blaming yourself when the system around the behavior stays the same. Required symbol: one clean loop arrow wrapping a single seed. Required palette: solid emerald green background (#0f8f5f), accent #d7ff3f, highlight #ff5a4f. Style variation: large sticker emblem. Make the symbol feel like one bold app sticker on a flat color field, with a thick clean outline and slight offset shadow. Use a playful, high-contrast Duolingo or Headway-like app illustration energy, but keep it premium. The emblem should occupy 45-55% of the upper canvas. Avoid tiny details. The result should be instantly recognizable from across the room. The background must remain one unbroken solid primary color across the entire image, including the bottom 44% where the title plate will sit. Do not add a darker footer, lower band, vignette, or separate bottom block. Make the books visibly different from each other by using the required primary background color strongly. The final set should not look like variations of the same navy/teal cover. Memorability standard: the image must read instantly at a tiny thumbnail size. If the idea needs more than one emblem, simplify it. Style: flat 2D illustration, bold geometric shapes, crisp edges, premium editorial taste, not photorealistic, not painterly, not collage. Composition standard: one centered emblem in the upper 56% of the 2:3 vertical canvas, generous negative space, no scene, no background environment, no depth-of-field, no realistic room, no hands. Simplicity limit: use one main object and at most one supporting shape. Avoid clusters, crowds, many lines, tiny parts, diagrams, dashboards, maps with detail, charts, documents, UI, and decorative clutter. Background standard: perfectly solid matte color field or a nearly solid field with only extremely subtle paper grain. No gradients behind the future title plate, no pattern fields, no texture-heavy backgrounds. Color standard: very high contrast and memorable. Use the required palette strongly so this book looks different from the others. Avoid beige, gray, washed-out neutrals, muddy gradients, monochrome palettes, and low-contrast pastel art. Hard no-text rule: no letters, no words, no book title, no author name, no numbers, no punctuation marks, no fake glyphs, no interface icons, no logos, no labels, no signage. Avoid literal speech bubbles, question marks, documents with writing, screens with UI, pages with text, book mockups, or any surface that could look like typography. Keep the bottom 44% visually calm and the same solid primary background color because the website will place matching title text over that area. Do not create a physical book cover, 3D book object, product photo, border, page spine, drop shadow, room background, hands, or a book sitting on a surface."
  },
  "four-thousand-weeks": {
    "title": "Four Thousand Weeks",
    "author": "Oliver Burkeman",
    "style": "sticker",
    "providerPrompt": "Create a text-free vertical icon illustration for a premium mobile learning app book tile. Concept seed: A counterweight to productivity culture: finite time means the central task is choosing, not optimizing everything. Reader situation: You are trying to become efficient enough to fit everything in and slowly realizing that the premise may be the trap. Required symbol: one hourglass reduced to two bold triangles. Required palette: solid aubergine violet background (#7a1f77), accent #ffd447, highlight #21d6ff. Style variation: large sticker emblem. Make the symbol feel like one bold app sticker on a flat color field, with a thick clean outline and slight offset shadow. Use a playful, high-contrast Duolingo or Headway-like app illustration energy, but keep it premium. The emblem should occupy 45-55% of the upper canvas. Avoid tiny details. The result should be instantly recognizable from across the room. The background must remain one unbroken solid primary color across the entire image, including the bottom 44% where the title plate will sit. Do not add a darker footer, lower band, vignette, or separate bottom block. Make the books visibly different from each other by using the required primary background color strongly. The final set should not look like variations of the same navy/teal cover. Memorability standard: the image must read instantly at a tiny thumbnail size. If the idea needs more than one emblem, simplify it. Style: flat 2D illustration, bold geometric shapes, crisp edges, premium editorial taste, not photorealistic, not painterly, not collage. Composition standard: one centered emblem in the upper 56% of the 2:3 vertical canvas, generous negative space, no scene, no background environment, no depth-of-field, no realistic room, no hands. Simplicity limit: use one main object and at most one supporting shape. Avoid clusters, crowds, many lines, tiny parts, diagrams, dashboards, maps with detail, charts, documents, UI, and decorative clutter. Background standard: perfectly solid matte color field or a nearly solid field with only extremely subtle paper grain. No gradients behind the future title plate, no pattern fields, no texture-heavy backgrounds. Color standard: very high contrast and memorable. Use the required palette strongly so this book looks different from the others. Avoid beige, gray, washed-out neutrals, muddy gradients, monochrome palettes, and low-contrast pastel art. Hard no-text rule: no letters, no words, no book title, no author name, no numbers, no punctuation marks, no fake glyphs, no interface icons, no logos, no labels, no signage. Avoid literal speech bubbles, question marks, documents with writing, screens with UI, pages with text, book mockups, or any surface that could look like typography. Keep the bottom 44% visually calm and the same solid primary background color because the website will place matching title text over that area. Do not create a physical book cover, 3D book object, product photo, border, page spine, drop shadow, room background, hands, or a book sitting on a surface."
  },
  "crucial-conversations": {
    "title": "Crucial Conversations",
    "author": "Kerry Patterson, Joseph Grenny, Ron McMillan, and Al Switzler",
    "style": "sticker",
    "providerPrompt": "Create a text-free vertical icon illustration for a premium mobile learning app book tile. Concept seed: A practical framework for conversations where stakes are high, opinions differ, and emotions can derail the outcome. Reader situation: You need to talk about conflict, feedback, performance, money, trust, or expectations without turning the conversation into avoidance or a fight. Required symbol: two simple speech stones meeting in the center. Required palette: solid raspberry pink background (#d8326f), accent #fff0d6, highlight #ff7a1a. Style variation: large sticker emblem. Make the symbol feel like one bold app sticker on a flat color field, with a thick clean outline and slight offset shadow. Use a playful, high-contrast Duolingo or Headway-like app illustration energy, but keep it premium. The emblem should occupy 45-55% of the upper canvas. Avoid tiny details. The result should be instantly recognizable from across the room. The background must remain one unbroken solid primary color across the entire image, including the bottom 44% where the title plate will sit. Do not add a darker footer, lower band, vignette, or separate bottom block. Make the books visibly different from each other by using the required primary background color strongly. The final set should not look like variations of the same navy/teal cover. Memorability standard: the image must read instantly at a tiny thumbnail size. If the idea needs more than one emblem, simplify it. Style: flat 2D illustration, bold geometric shapes, crisp edges, premium editorial taste, not photorealistic, not painterly, not collage. Composition standard: one centered emblem in the upper 56% of the 2:3 vertical canvas, generous negative space, no scene, no background environment, no depth-of-field, no realistic room, no hands. Simplicity limit: use one main object and at most one supporting shape. Avoid clusters, crowds, many lines, tiny parts, diagrams, dashboards, maps with detail, charts, documents, UI, and decorative clutter. Background standard: perfectly solid matte color field or a nearly solid field with only extremely subtle paper grain. No gradients behind the future title plate, no pattern fields, no texture-heavy backgrounds. Color standard: very high contrast and memorable. Use the required palette strongly so this book looks different from the others. Avoid beige, gray, washed-out neutrals, muddy gradients, monochrome palettes, and low-contrast pastel art. Hard no-text rule: no letters, no words, no book title, no author name, no numbers, no punctuation marks, no fake glyphs, no interface icons, no logos, no labels, no signage. Avoid literal speech bubbles, question marks, documents with writing, screens with UI, pages with text, book mockups, or any surface that could look like typography. Keep the bottom 44% visually calm and the same solid primary background color because the website will place matching title text over that area. Do not create a physical book cover, 3D book object, product photo, border, page spine, drop shadow, room background, hands, or a book sitting on a surface."
  },
  "never-split-the-difference": {
    "title": "Never Split the Difference",
    "author": "Chris Voss with Tahl Raz",
    "style": "sticker",
    "providerPrompt": "Create a text-free vertical icon illustration for a premium mobile learning app book tile. Concept seed: A negotiation playbook centered on tactical empathy, listening, labels, mirrors, and calibrated questions. Reader situation: You are negotiating salary, scope, price, deadlines, or conflict and your default move is either over-explaining or giving ground too quickly. Required symbol: one balanced scale with two uneven circles. Required palette: solid black cherry background (#8f1249), accent #00d9ff, highlight #ffbd2e. Style variation: large sticker emblem. Make the symbol feel like one bold app sticker on a flat color field, with a thick clean outline and slight offset shadow. Use a playful, high-contrast Duolingo or Headway-like app illustration energy, but keep it premium. The emblem should occupy 45-55% of the upper canvas. Avoid tiny details. The result should be instantly recognizable from across the room. The background must remain one unbroken solid primary color across the entire image, including the bottom 44% where the title plate will sit. Do not add a darker footer, lower band, vignette, or separate bottom block. Make the books visibly different from each other by using the required primary background color strongly. The final set should not look like variations of the same navy/teal cover. Memorability standard: the image must read instantly at a tiny thumbnail size. If the idea needs more than one emblem, simplify it. Style: flat 2D illustration, bold geometric shapes, crisp edges, premium editorial taste, not photorealistic, not painterly, not collage. Composition standard: one centered emblem in the upper 56% of the 2:3 vertical canvas, generous negative space, no scene, no background environment, no depth-of-field, no realistic room, no hands. Simplicity limit: use one main object and at most one supporting shape. Avoid clusters, crowds, many lines, tiny parts, diagrams, dashboards, maps with detail, charts, documents, UI, and decorative clutter. Background standard: perfectly solid matte color field or a nearly solid field with only extremely subtle paper grain. No gradients behind the future title plate, no pattern fields, no texture-heavy backgrounds. Color standard: very high contrast and memorable. Use the required palette strongly so this book looks different from the others. Avoid beige, gray, washed-out neutrals, muddy gradients, monochrome palettes, and low-contrast pastel art. Hard no-text rule: no letters, no words, no book title, no author name, no numbers, no punctuation marks, no fake glyphs, no interface icons, no logos, no labels, no signage. Avoid literal speech bubbles, question marks, documents with writing, screens with UI, pages with text, book mockups, or any surface that could look like typography. Keep the bottom 44% visually calm and the same solid primary background color because the website will place matching title text over that area. Do not create a physical book cover, 3D book object, product photo, border, page spine, drop shadow, room background, hands, or a book sitting on a surface."
  },
  "the-effective-executive": {
    "title": "The Effective Executive",
    "author": "Peter F. Drucker",
    "style": "sticker",
    "providerPrompt": "Create a text-free vertical icon illustration for a premium mobile learning app book tile. Concept seed: A compact management classic about time, contribution, strengths, priorities, and decision effectiveness. Reader situation: You are busy, responsible for outcomes through other people, and unsure whether your activity is actually producing contribution. Required symbol: one calendar square with a chess piece silhouette. Required palette: solid graphite charcoal background (#2f3238), accent #ffbd2e, highlight #00d9ff. Style variation: large sticker emblem. Make the symbol feel like one bold app sticker on a flat color field, with a thick clean outline and slight offset shadow. Use a playful, high-contrast Duolingo or Headway-like app illustration energy, but keep it premium. The emblem should occupy 45-55% of the upper canvas. Avoid tiny details. The result should be instantly recognizable from across the room. The background must remain one unbroken solid primary color across the entire image, including the bottom 44% where the title plate will sit. Do not add a darker footer, lower band, vignette, or separate bottom block. Make the books visibly different from each other by using the required primary background color strongly. The final set should not look like variations of the same navy/teal cover. Memorability standard: the image must read instantly at a tiny thumbnail size. If the idea needs more than one emblem, simplify it. Style: flat 2D illustration, bold geometric shapes, crisp edges, premium editorial taste, not photorealistic, not painterly, not collage. Composition standard: one centered emblem in the upper 56% of the 2:3 vertical canvas, generous negative space, no scene, no background environment, no depth-of-field, no realistic room, no hands. Simplicity limit: use one main object and at most one supporting shape. Avoid clusters, crowds, many lines, tiny parts, diagrams, dashboards, maps with detail, charts, documents, UI, and decorative clutter. Background standard: perfectly solid matte color field or a nearly solid field with only extremely subtle paper grain. No gradients behind the future title plate, no pattern fields, no texture-heavy backgrounds. Color standard: very high contrast and memorable. Use the required palette strongly so this book looks different from the others. Avoid beige, gray, washed-out neutrals, muddy gradients, monochrome palettes, and low-contrast pastel art. Hard no-text rule: no letters, no words, no book title, no author name, no numbers, no punctuation marks, no fake glyphs, no interface icons, no logos, no labels, no signage. Avoid literal speech bubbles, question marks, documents with writing, screens with UI, pages with text, book mockups, or any surface that could look like typography. Keep the bottom 44% visually calm and the same solid primary background color because the website will place matching title text over that area. Do not create a physical book cover, 3D book object, product photo, border, page spine, drop shadow, room background, hands, or a book sitting on a surface."
  },
  "high-output-management": {
    "title": "High Output Management",
    "author": "Andrew S. Grove",
    "style": "sticker",
    "providerPrompt": "Create a text-free vertical icon illustration for a premium mobile learning app book tile. Concept seed: A manager's operating manual for increasing the output of a team through leverage, clear processes, meetings, and coaching. Reader situation: You manage people and need a practical model for delegation, one-on-ones, training, and team output. Required symbol: one factory dial with a single rising needle. Required palette: solid indigo navy background (#18206f), accent #ff8a1f, highlight #c8ff2d. Style variation: large sticker emblem. Make the symbol feel like one bold app sticker on a flat color field, with a thick clean outline and slight offset shadow. Use a playful, high-contrast Duolingo or Headway-like app illustration energy, but keep it premium. The emblem should occupy 45-55% of the upper canvas. Avoid tiny details. The result should be instantly recognizable from across the room. The background must remain one unbroken solid primary color across the entire image, including the bottom 44% where the title plate will sit. Do not add a darker footer, lower band, vignette, or separate bottom block. Make the books visibly different from each other by using the required primary background color strongly. The final set should not look like variations of the same navy/teal cover. Memorability standard: the image must read instantly at a tiny thumbnail size. If the idea needs more than one emblem, simplify it. Style: flat 2D illustration, bold geometric shapes, crisp edges, premium editorial taste, not photorealistic, not painterly, not collage. Composition standard: one centered emblem in the upper 56% of the 2:3 vertical canvas, generous negative space, no scene, no background environment, no depth-of-field, no realistic room, no hands. Simplicity limit: use one main object and at most one supporting shape. Avoid clusters, crowds, many lines, tiny parts, diagrams, dashboards, maps with detail, charts, documents, UI, and decorative clutter. Background standard: perfectly solid matte color field or a nearly solid field with only extremely subtle paper grain. No gradients behind the future title plate, no pattern fields, no texture-heavy backgrounds. Color standard: very high contrast and memorable. Use the required palette strongly so this book looks different from the others. Avoid beige, gray, washed-out neutrals, muddy gradients, monochrome palettes, and low-contrast pastel art. Hard no-text rule: no letters, no words, no book title, no author name, no numbers, no punctuation marks, no fake glyphs, no interface icons, no logos, no labels, no signage. Avoid literal speech bubbles, question marks, documents with writing, screens with UI, pages with text, book mockups, or any surface that could look like typography. Keep the bottom 44% visually calm and the same solid primary background color because the website will place matching title text over that area. Do not create a physical book cover, 3D book object, product photo, border, page spine, drop shadow, room background, hands, or a book sitting on a surface."
  },
  "the-checklist-manifesto": {
    "title": "The Checklist Manifesto",
    "author": "Atul Gawande",
    "style": "sticker",
    "providerPrompt": "Create a text-free vertical icon illustration for a premium mobile learning app book tile. Concept seed: A case for simple checklists as a way to reduce avoidable failure in complex work. Reader situation: Your team keeps making preventable mistakes, but adding more process feels like bureaucracy. Required symbol: one clipboard shape with three abstract ticks, no writing. Required palette: solid surgical green background (#0c7f3a), accent #fff0d6, highlight #ff5f57. Style variation: large sticker emblem. Make the symbol feel like one bold app sticker on a flat color field, with a thick clean outline and slight offset shadow. Use a playful, high-contrast Duolingo or Headway-like app illustration energy, but keep it premium. The emblem should occupy 45-55% of the upper canvas. Avoid tiny details. The result should be instantly recognizable from across the room. The background must remain one unbroken solid primary color across the entire image, including the bottom 44% where the title plate will sit. Do not add a darker footer, lower band, vignette, or separate bottom block. Make the books visibly different from each other by using the required primary background color strongly. The final set should not look like variations of the same navy/teal cover. Memorability standard: the image must read instantly at a tiny thumbnail size. If the idea needs more than one emblem, simplify it. Style: flat 2D illustration, bold geometric shapes, crisp edges, premium editorial taste, not photorealistic, not painterly, not collage. Composition standard: one centered emblem in the upper 56% of the 2:3 vertical canvas, generous negative space, no scene, no background environment, no depth-of-field, no realistic room, no hands. Simplicity limit: use one main object and at most one supporting shape. Avoid clusters, crowds, many lines, tiny parts, diagrams, dashboards, maps with detail, charts, documents, UI, and decorative clutter. Background standard: perfectly solid matte color field or a nearly solid field with only extremely subtle paper grain. No gradients behind the future title plate, no pattern fields, no texture-heavy backgrounds. Color standard: very high contrast and memorable. Use the required palette strongly so this book looks different from the others. Avoid beige, gray, washed-out neutrals, muddy gradients, monochrome palettes, and low-contrast pastel art. Hard no-text rule: no letters, no words, no book title, no author name, no numbers, no punctuation marks, no fake glyphs, no interface icons, no logos, no labels, no signage. Avoid literal speech bubbles, question marks, documents with writing, screens with UI, pages with text, book mockups, or any surface that could look like typography. Keep the bottom 44% visually calm and the same solid primary background color because the website will place matching title text over that area. Do not create a physical book cover, 3D book object, product photo, border, page spine, drop shadow, room background, hands, or a book sitting on a surface."
  },
  "so-good-they-cant-ignore-you": {
    "title": "So Good They Can't Ignore You",
    "author": "Cal Newport",
    "style": "sticker",
    "providerPrompt": "Create a text-free vertical icon illustration for a premium mobile learning app book tile. Concept seed: A career argument that rare and valuable work usually comes from building rare and valuable skills first. Reader situation: You are trying to choose a career path and suspect that advice to simply follow your passion is too thin to guide real decisions. Required symbol: one chisel carving a sharp star from stone. Required palette: solid ultramarine background (#2341ff), accent #ff8a1f, highlight #ffffff. Style variation: large sticker emblem. Make the symbol feel like one bold app sticker on a flat color field, with a thick clean outline and slight offset shadow. Use a playful, high-contrast Duolingo or Headway-like app illustration energy, but keep it premium. The emblem should occupy 45-55% of the upper canvas. Avoid tiny details. The result should be instantly recognizable from across the room. The background must remain one unbroken solid primary color across the entire image, including the bottom 44% where the title plate will sit. Do not add a darker footer, lower band, vignette, or separate bottom block. Make the books visibly different from each other by using the required primary background color strongly. The final set should not look like variations of the same navy/teal cover. Memorability standard: the image must read instantly at a tiny thumbnail size. If the idea needs more than one emblem, simplify it. Style: flat 2D illustration, bold geometric shapes, crisp edges, premium editorial taste, not photorealistic, not painterly, not collage. Composition standard: one centered emblem in the upper 56% of the 2:3 vertical canvas, generous negative space, no scene, no background environment, no depth-of-field, no realistic room, no hands. Simplicity limit: use one main object and at most one supporting shape. Avoid clusters, crowds, many lines, tiny parts, diagrams, dashboards, maps with detail, charts, documents, UI, and decorative clutter. Background standard: perfectly solid matte color field or a nearly solid field with only extremely subtle paper grain. No gradients behind the future title plate, no pattern fields, no texture-heavy backgrounds. Color standard: very high contrast and memorable. Use the required palette strongly so this book looks different from the others. Avoid beige, gray, washed-out neutrals, muddy gradients, monochrome palettes, and low-contrast pastel art. Hard no-text rule: no letters, no words, no book title, no author name, no numbers, no punctuation marks, no fake glyphs, no interface icons, no logos, no labels, no signage. Avoid literal speech bubbles, question marks, documents with writing, screens with UI, pages with text, book mockups, or any surface that could look like typography. Keep the bottom 44% visually calm and the same solid primary background color because the website will place matching title text over that area. Do not create a physical book cover, 3D book object, product photo, border, page spine, drop shadow, room background, hands, or a book sitting on a surface."
  },
  "designing-your-life": {
    "title": "Designing Your Life",
    "author": "Bill Burnett and Dave Evans",
    "style": "sticker",
    "providerPrompt": "Create a text-free vertical icon illustration for a premium mobile learning app book tile. Concept seed: A design-thinking approach to career and life decisions: prototype paths instead of trying to think your way into certainty. Reader situation: You feel stuck between possible lives and need a way to test directions without treating every decision as irreversible. Required symbol: one compass needle inside a simple path ring. Required palette: solid clear cobalt blue background (#1458e8), accent #ff8a1f, highlight #83ffd2. Style variation: large sticker emblem. Make the symbol feel like one bold app sticker on a flat color field, with a thick clean outline and slight offset shadow. Use a playful, high-contrast Duolingo or Headway-like app illustration energy, but keep it premium. The emblem should occupy 45-55% of the upper canvas. Avoid tiny details. The result should be instantly recognizable from across the room. The background must remain one unbroken solid primary color across the entire image, including the bottom 44% where the title plate will sit. Do not add a darker footer, lower band, vignette, or separate bottom block. Make the books visibly different from each other by using the required primary background color strongly. The final set should not look like variations of the same navy/teal cover. Memorability standard: the image must read instantly at a tiny thumbnail size. If the idea needs more than one emblem, simplify it. Style: flat 2D illustration, bold geometric shapes, crisp edges, premium editorial taste, not photorealistic, not painterly, not collage. Composition standard: one centered emblem in the upper 56% of the 2:3 vertical canvas, generous negative space, no scene, no background environment, no depth-of-field, no realistic room, no hands. Simplicity limit: use one main object and at most one supporting shape. Avoid clusters, crowds, many lines, tiny parts, diagrams, dashboards, maps with detail, charts, documents, UI, and decorative clutter. Background standard: perfectly solid matte color field or a nearly solid field with only extremely subtle paper grain. No gradients behind the future title plate, no pattern fields, no texture-heavy backgrounds. Color standard: very high contrast and memorable. Use the required palette strongly so this book looks different from the others. Avoid beige, gray, washed-out neutrals, muddy gradients, monochrome palettes, and low-contrast pastel art. Hard no-text rule: no letters, no words, no book title, no author name, no numbers, no punctuation marks, no fake glyphs, no interface icons, no logos, no labels, no signage. Avoid literal speech bubbles, question marks, documents with writing, screens with UI, pages with text, book mockups, or any surface that could look like typography. Keep the bottom 44% visually calm and the same solid primary background color because the website will place matching title text over that area. Do not create a physical book cover, 3D book object, product photo, border, page spine, drop shadow, room background, hands, or a book sitting on a surface."
  }
}
